{
  "id": "1bDWGdIC2hardyt55nlQgG",
  "name": "\"Weird Al\" Yankovic",
  "followers": 914892,
  "monthlyListeners": 1261727,
  "topCities": {
    "items": [
      {
        "city": "Chicago",
        "country": "US",
        "numberOfListeners": 19468,
        "region": "IL"
      },
      {
        "city": "Sydney",
        "country": "AU",
        "numberOfListeners": 18520,
        "region": "NSW"
      },
      {
        "city": "Melbourne",
        "country": "AU",
        "numberOfListeners": 17450,
        "region": "VIC"
      },
      {
        "city": "London",
        "country": "GB",
        "numberOfListeners": 16699,
        "region": "ENG"
      },
      {
        "city": "Seattle",
        "country": "US",
        "numberOfListeners": 14582,
        "region": "WA"
      }
    ]
  },
  "worldRank": 0
}
