{
  "id": "3dUu9IeP8wOWOFSMlNLdkD",
  "name": "Alexander",
  "followers": 1358,
  "monthlyListeners": 20764,
  "topCities": {
    "items": [
      {
        "city": "Prague",
        "country": "CZ",
        "numberOfListeners": 235,
        "region": "10"
      },
      {
        "city": "Berlin",
        "country": "DE",
        "numberOfListeners": 209,
        "region": "BE"
      },
      {
        "city": "Warsaw",
        "country": "PL",
        "numberOfListeners": 189,
        "region": "14"
      },
      {
        "city": "Paris",
        "country": "FR",
        "numberOfListeners": 176,
        "region": "IDF"
      },
      {
        "city": "Sydney",
        "country": "AU",
        "numberOfListeners": 165,
        "region": "NSW"
      }
    ]
  },
  "worldRank": 0
}
