{
  "id": "0m9dBOIW13zLL3ItoEcoa1",
  "name": "Amin Nordin",
  "followers": 145,
  "monthlyListeners": 2714,
  "topCities": {
    "items": [
      {
        "city": "Guwahati",
        "country": "IN",
        "numberOfListeners": 238,
        "region": "AS"
      },
      {
        "city": "Shillong",
        "country": "IN",
        "numberOfListeners": 133,
        "region": "ML"
      },
      {
        "city": "Taipei",
        "country": "TW",
        "numberOfListeners": 97,
        "region": "TPE"
      },
      {
        "city": "Imphal",
        "country": "IN",
        "numberOfListeners": 90,
        "region": "MN"
      },
      {
        "city": "Jakarta",
        "country": "ID",
        "numberOfListeners": 84,
        "region": "JK"
      }
    ]
  },
  "worldRank": 0
}
