{
  "id": "7hIqJfRYGBWWT1Qxu6Cpd2",
  "name": "Andy Rivera",
  "followers": 3062529,
  "monthlyListeners": 5357476,
  "topCities": {
    "items": [
      {
        "city": "Bogotá",
        "country": "CO",
        "numberOfListeners": 1218628,
        "region": "DC"
      },
      {
        "city": "Medellín",
        "country": "CO",
        "numberOfListeners": 605684,
        "region": "ANT"
      },
      {
        "city": "Santiago de Cali",
        "country": "CO",
        "numberOfListeners": 277688,
        "region": "VAC"
      },
      {
        "city": "Barranquilla",
        "country": "CO",
        "numberOfListeners": 199024,
        "region": "ATL"
      },
      {
        "city": "Santiago",
        "country": "CL",
        "numberOfListeners": 181298,
        "region": "RM"
      }
    ]
  },
  "worldRank": 0
}
