{
  "id": "13bDjug9N0pyv3ZUINjkDV",
  "name": "Bausa",
  "followers": 1086286,
  "monthlyListeners": 5829031,
  "topCities": {
    "items": [
      {
        "city": "Berlin",
        "country": "DE",
        "numberOfListeners": 597809,
        "region": "BE"
      },
      {
        "city": "Hamburg",
        "country": "DE",
        "numberOfListeners": 486807,
        "region": "HH"
      },
      {
        "city": "Frankfurt am Main",
        "country": "DE",
        "numberOfListeners": 446410,
        "region": "HE"
      },
      {
        "city": "Munich",
        "country": "DE",
        "numberOfListeners": 389413,
        "region": "BY"
      },
      {
        "city": "Stuttgart",
        "country": "DE",
        "numberOfListeners": 344622,
        "region": "BW"
      }
    ]
  },
  "worldRank": 0
}
