{
  "id": "5isqImG0rLfAgBJSPMEVXF",
  "name": "Blonde Redhead",
  "followers": 346962,
  "monthlyListeners": 1044944,
  "topCities": {
    "items": [
      {
        "city": "Los Angeles",
        "country": "US",
        "numberOfListeners": 16933,
        "region": "CA"
      },
      {
        "city": "London",
        "country": "GB",
        "numberOfListeners": 15517,
        "region": "ENG"
      },
      {
        "city": "Istanbul",
        "country": "TR",
        "numberOfListeners": 13490,
        "region": "34"
      },
      {
        "city": "Melbourne",
        "country": "AU",
        "numberOfListeners": 12961,
        "region": "VIC"
      },
      {
        "city": "Paris",
        "country": "FR",
        "numberOfListeners": 12818,
        "region": "IDF"
      }
    ]
  },
  "worldRank": 0
}
