{
  "id": "4mLJ3XfOM5FPjSAWdQ2Jk7",
  "name": "Dr. Dog",
  "followers": 556507,
  "monthlyListeners": 5303656,
  "topCities": {
    "items": [
      {
        "city": "Jakarta",
        "country": "ID",
        "numberOfListeners": 94913,
        "region": "JK"
      },
      {
        "city": "Chicago",
        "country": "US",
        "numberOfListeners": 63841,
        "region": "IL"
      },
      {
        "city": "Los Angeles",
        "country": "US",
        "numberOfListeners": 56540,
        "region": "CA"
      },
      {
        "city": "Sydney",
        "country": "AU",
        "numberOfListeners": 56017,
        "region": "NSW"
      },
      {
        "city": "New York City",
        "country": "US",
        "numberOfListeners": 53473,
        "region": "NY"
      }
    ]
  },
  "worldRank": 0
}
