{
  "id": "3TVXtAsR1Inumwj472S9r4",
  "name": "Drake",
  "followers": 91962369,
  "monthlyListeners": 76008860,
  "topCities": {
    "items": [
      {
        "city": "London",
        "country": "GB",
        "numberOfListeners": 1625328,
        "region": "ENG"
      },
      {
        "city": "Los Angeles",
        "country": "US",
        "numberOfListeners": 1141069,
        "region": "CA"
      },
      {
        "city": "New York City",
        "country": "US",
        "numberOfListeners": 1105276,
        "region": "NY"
      },
      {
        "city": "Chicago",
        "country": "US",
        "numberOfListeners": 1031024,
        "region": "IL"
      },
      {
        "city": "Toronto",
        "country": "CA",
        "numberOfListeners": 998326,
        "region": "ON"
      }
    ]
  },
  "worldRank": 12
}
