{
  "id": "2dNnJIEECfh07bv1jwmfTL",
  "name": "Emma Volard",
  "followers": 1949,
  "monthlyListeners": 3686,
  "topCities": {
    "items": [
      {
        "city": "Melbourne",
        "country": "AU",
        "numberOfListeners": 378,
        "region": "VIC"
      },
      {
        "city": "Sydney",
        "country": "AU",
        "numberOfListeners": 198,
        "region": "NSW"
      },
      {
        "city": "Tokyo",
        "country": "JP",
        "numberOfListeners": 190,
        "region": "13"
      },
      {
        "city": "Brisbane",
        "country": "AU",
        "numberOfListeners": 79,
        "region": "QLD"
      },
      {
        "city": "Santiago",
        "country": "CL",
        "numberOfListeners": 57,
        "region": "RM"
      }
    ]
  },
  "worldRank": 0
}
