{
  "id": "05etL4pzWd6TSv1x5WrlG3",
  "name": "Faheem Abdullah",
  "followers": 58633,
  "monthlyListeners": 5151580,
  "topCities": {
    "items": [
      {
        "city": "Delhi",
        "country": "IN",
        "numberOfListeners": 441814,
        "region": "DL"
      },
      {
        "city": "Mumbai",
        "country": "IN",
        "numberOfListeners": 419285,
        "region": "MH"
      },
      {
        "city": "New Delhi",
        "country": "IN",
        "numberOfListeners": 357672,
        "region": "DL"
      },
      {
        "city": "Pune",
        "country": "IN",
        "numberOfListeners": 318410,
        "region": "MH"
      },
      {
        "city": "Kolkata",
        "country": "IN",
        "numberOfListeners": 272749,
        "region": "WB"
      }
    ]
  },
  "worldRank": 0
}
