{
  "id": "5gqmbbfjcikQBzPB5Hv13I",
  "name": "Gazo",
  "followers": 3112893,
  "monthlyListeners": 7058136,
  "topCities": {
    "items": [
      {
        "city": "Paris",
        "country": "FR",
        "numberOfListeners": 1075686,
        "region": "IDF"
      },
      {
        "city": "Brussels",
        "country": "BE",
        "numberOfListeners": 285563,
        "region": "BRU"
      },
      {
        "city": "Lyon",
        "country": "FR",
        "numberOfListeners": 229231,
        "region": "ARA"
      },
      {
        "city": "Lille",
        "country": "FR",
        "numberOfListeners": 190625,
        "region": "HDF"
      },
      {
        "city": "Marseille",
        "country": "FR",
        "numberOfListeners": 165094,
        "region": "PAC"
      }
    ]
  },
  "worldRank": 0
}
