{
  "id": "3AA28KZvwAUcZuOKwyblJQ",
  "name": "Gorillaz",
  "followers": 12129699,
  "monthlyListeners": 24631160,
  "topCities": {
    "items": [
      {
        "city": "Mexico City",
        "country": "MX",
        "numberOfListeners": 520102,
        "region": "CMX"
      },
      {
        "city": "Santiago",
        "country": "CL",
        "numberOfListeners": 408793,
        "region": "RM"
      },
      {
        "city": "London",
        "country": "GB",
        "numberOfListeners": 398632,
        "region": "ENG"
      },
      {
        "city": "São Paulo",
        "country": "BR",
        "numberOfListeners": 299223,
        "region": "SP"
      },
      {
        "city": "Sydney",
        "country": "AU",
        "numberOfListeners": 295080,
        "region": "NSW"
      }
    ]
  },
  "worldRank": 233
}
