{
  "id": "7EGwUS3c5dXduO4sMyLWC5",
  "name": "Houndmouth",
  "followers": 307682,
  "monthlyListeners": 1692355,
  "topCities": {
    "items": [
      {
        "city": "Denver",
        "country": "US",
        "numberOfListeners": 38797,
        "region": "CO"
      },
      {
        "city": "Chicago",
        "country": "US",
        "numberOfListeners": 38686,
        "region": "IL"
      },
      {
        "city": "New York City",
        "country": "US",
        "numberOfListeners": 34902,
        "region": "NY"
      },
      {
        "city": "Seattle",
        "country": "US",
        "numberOfListeners": 27048,
        "region": "WA"
      },
      {
        "city": "Charlotte",
        "country": "US",
        "numberOfListeners": 26691,
        "region": "NC"
      }
    ]
  },
  "worldRank": 0
}
