{
  "id": "0bMt8SJlp0gFRUufzifS05",
  "name": "K.I.Z",
  "followers": 916535,
  "monthlyListeners": 1985703,
  "topCities": {
    "items": [
      {
        "city": "Berlin",
        "country": "DE",
        "numberOfListeners": 249530,
        "region": "BE"
      },
      {
        "city": "Hamburg",
        "country": "DE",
        "numberOfListeners": 184079,
        "region": "HH"
      },
      {
        "city": "Frankfurt am Main",
        "country": "DE",
        "numberOfListeners": 162018,
        "region": "HE"
      },
      {
        "city": "Munich",
        "country": "DE",
        "numberOfListeners": 141258,
        "region": "BY"
      },
      {
        "city": "Stuttgart",
        "country": "DE",
        "numberOfListeners": 114457,
        "region": "BW"
      }
    ]
  },
  "worldRank": 0
}
