{
  "id": "2W6WP4pHQTFlbr2z9S4n54",
  "name": "Kordhell",
  "followers": 1332221,
  "monthlyListeners": 9119501,
  "topCities": {
    "items": [
      {
        "city": "Istanbul",
        "country": "TR",
        "numberOfListeners": 105142,
        "region": "34"
      },
      {
        "city": "Mumbai",
        "country": "IN",
        "numberOfListeners": 91278,
        "region": "MH"
      },
      {
        "city": "Jakarta",
        "country": "ID",
        "numberOfListeners": 87706,
        "region": "JK"
      },
      {
        "city": "Bengaluru",
        "country": "IN",
        "numberOfListeners": 84955,
        "region": "KA"
      },
      {
        "city": "São Paulo",
        "country": "BR",
        "numberOfListeners": 79885,
        "region": "SP"
      }
    ]
  },
  "worldRank": 0
}
