{
  "id": "3qvcCP2J0fWi0m0uQDUf6r",
  "name": "Luan Santana",
  "followers": 8033061,
  "monthlyListeners": 12498524,
  "topCities": {
    "items": [
      {
        "city": "São Paulo",
        "country": "BR",
        "numberOfListeners": 1968645,
        "region": "SP"
      },
      {
        "city": "Belo Horizonte",
        "country": "BR",
        "numberOfListeners": 754952,
        "region": "MG"
      },
      {
        "city": "Curitiba",
        "country": "BR",
        "numberOfListeners": 628491,
        "region": "PR"
      },
      {
        "city": "Campinas",
        "country": "BR",
        "numberOfListeners": 621980,
        "region": "SP"
      },
      {
        "city": "Brasília",
        "country": "BR",
        "numberOfListeners": 558257,
        "region": "DF"
      }
    ]
  },
  "worldRank": 0
}
