{
  "id": "4AKwRarlmsUlLjIwt38NLw",
  "name": "Ofenbach",
  "followers": 624695,
  "monthlyListeners": 15661954,
  "topCities": {
    "items": [
      {
        "city": "Paris",
        "country": "FR",
        "numberOfListeners": 416898,
        "region": "IDF"
      },
      {
        "city": "Amsterdam",
        "country": "NL",
        "numberOfListeners": 243852,
        "region": "NH"
      },
      {
        "city": "Warsaw",
        "country": "PL",
        "numberOfListeners": 236552,
        "region": "14"
      },
      {
        "city": "Berlin",
        "country": "DE",
        "numberOfListeners": 214905,
        "region": "BE"
      },
      {
        "city": "Brussels",
        "country": "BE",
        "numberOfListeners": 213830,
        "region": "BRU"
      }
    ]
  },
  "worldRank": 0
}
