{
  "id": "3jOstUTkEu2JkjvRdBA5Gu",
  "name": "Weezer",
  "followers": 3790877,
  "monthlyListeners": 15051393,
  "topCities": {
    "items": [
      {
        "city": "Los Angeles",
        "country": "US",
        "numberOfListeners": 235103,
        "region": "CA"
      },
      {
        "city": "Chicago",
        "country": "US",
        "numberOfListeners": 225655,
        "region": "IL"
      },
      {
        "city": "Sydney",
        "country": "AU",
        "numberOfListeners": 182678,
        "region": "NSW"
      },
      {
        "city": "New York City",
        "country": "US",
        "numberOfListeners": 179431,
        "region": "NY"
      },
      {
        "city": "Toronto",
        "country": "CA",
        "numberOfListeners": 175611,
        "region": "ON"
      }
    ]
  },
  "worldRank": 0
}
