{"v":1,"i":"2QWIScpFDNxmS6ZEMIUvgm","n":"Julieta Venegas","p":"ab6761610000e5eb44270f00ab4402b3fd91bad1","today":{"d":"2025-11-10","r":null,"ml":17312238,"f":3336706,"dr":null,"g1":-11644,"g7":29912,"g30":0,"fs":0.001,"ms":0.0},"meta":{"firstSeen":"2025-10-25","first500":null,"last500":null,"timesEntered500":0,"days500":0,"br":null},"bio":"Julieta Venegas is a mexican singer, songwriter, and producer, with 9 studio albums: Aquí (1996) Bueninvento (2000), Sí (2003), Limon y Sal (2006), Otra Cosa (2009), Los Momentos (2011), Algo Sucede (2015) and an MTV Unplugged (2008) Tu Historia (2022) She got started in music as a little girl, when she studied classical piano, after that she has been involved in many bands, as a keyboard player, songwriter, and singer. She has toured in many countries like Mexico, USA, Brazil, Europe, and South America.","gallery":["ab6761670000ecd404094d40c2776bac8b57fc10","ab6761670000ecd4af485e0e40fd6b811fc824ef","ab6761670000ecd4bf82e1a7d76ae861a4fbb9d1","ab6761670000ecd4d4be6520ad5372520689233e","ab6761670000ecd4348bf1e46a801f5a8498a017","ab6761670000ecd4ce02eb68bbeb2c7d619e7c78"],"series":{"fields":["d","ml","f","r"],"rows":[["2025-10-25",17437950,3305495,null],["2025-10-26",17440409,3307693,null],["2025-10-27",17406368,3309769,null],["2025-10-28",17393172,3311672,null],["2025-10-29",17388808,3314211,null],["2025-10-30",17355446,3315296,null],["2025-10-31",17326284,3317117,null],["2025-11-01",17283033,3318878,null],["2025-11-02",17258843,3320635,null],["2025-11-03",17282326,3322491,null],["2025-11-04",17299145,3324466,null],["2025-11-05",17295554,3326460,null],["2025-11-06",17308204,3328517,null],["2025-11-07",17345582,3330580,null],["2025-11-08",17345582,3332576,null],["2025-11-09",17323882,3334712,null],["2025-11-10",17312238,3336706,null]]},"topTracks":{"fields":["i","n","pl","img","preview","licensor","language","isrc","label","rd","canvas"],"rows":[["100Tm6z29RfHTdUQ6NIs0s","Me Voy",645392723,"ab67616d00001e02a043fa84be801dca33dacca1","a94ceef62760bcf8a2eec35ddcd4dd405f64f27b","Sony Music Entertainment","es","MXF010600165","Ariola","2006-05-25",null],["04x1x0L8BYyIv1XlcJxWfi","Lo Siento BB:/",1104430886,"ab67616d00001e02f885fb64a381318a1c9c14e4","44cf2fd01f9079f50bf2d92e816d14083fada389","Virgin Music Group / InGrooves","es","USA2P2135437","NEON16, LLC","2023-06-29","https://canvaz.scdn.co/upload/artist/0GM7qgcRCORpGnfcN2tCiB/video/0bfb5194b5004477b2bb13d3e12bc196.cnvs.mp4"],["7dITAq1YP5e0kTcaDq4YWI","Limón y Sal",414663303,"ab67616d00001e02a043fa84be801dca33dacca1","620487e1ca2640bd3e0b201ac6a83690e50b2b6c","Sony Music Entertainment","es","MXF010600234","Ariola","2006-05-25",null],["05iMQqncVBIm4AE26EvaTL","Andar Conmigo",366036065,"ab67616d00001e02c0071a27b79e46c09eef7caa","225917690c2e59eaa0e47f5a7eb1cd5a73102b5f","Sony Music Entertainment","es","MXF010300339","Ariola","2003-11-18",null],["3IQulMlnptSOhfblnvFuvN","A Donde Va El Viento (Canción de la Serie Original de Prime)",93785516,"ab67616d00001e020f9b7d9ce7b7c069eef25bc9","b52cb63066731f2b7a52eaa2bdb2f51a152b9c06","Foundation Media","es","QZAKB2411010","Amazon Content Services, LLC","2024-07-11",null],["4m3vLNZkFAjm30XxPXf7E3","Eres para Mí",339741818,"ab67616d00001e02a043fa84be801dca33dacca1","b2469a2a45271650b1a91653656ffcbcf0b88ea1","Sony Music Entertainment","es","MXF010600240","Ariola","2006-05-25",null],["2NsMwNWumJXCdTg2IZCLZ5","Lento",273485149,"ab67616d00001e02c0071a27b79e46c09eef7caa","4468758a684a1522920ee8914540a59ee9ac554d","Sony Music Entertainment","es","MXF010300338","Ariola","2003-11-18","https://canvaz.scdn.co/upload/artist/2QWIScpFDNxmS6ZEMIUvgm/video/e1060fd7199945b98e21ab4954672720.cnvs.mp4"],["2KyntP9bkdZzyA4DBZXJP3","Dos Soledades",87054492,"ab67616d00001e02e3fa8f6985188babc6be4de2",null,"The Orchard","es","MXB131500007","Altafonte under exclusive license from Ohanian S. de R.L. de C.V.","2015-08-14",null],["7GO6pBFbieZ30NjGIp2LP5","Nada Fue Un Error - Live In Spain / 2005",160327481,"ab67616d00001e020af51b9385bfdefc8673159b","49a6380e67fbdb0eb67106f0c30d816baf435663","Universal Music Group","es","ES5700500260","Universal Music Spain S.L.","2005-01-01",null],["7mJG18yZGq0aXKWNtK3FQf","Algo Está Cambiando",83924678,"ab67616d00001e02c0071a27b79e46c09eef7caa","761dbdd1738b65e025016c07bc8a3ef0a8f39860","Sony Music Entertainment","es","MXF010300340","Ariola","2003-11-18",null],["2c6xAssXKcQ9NbcrMguJ5O","Dos Soledades",86951516,"ab67616d00001e02f13e1e71a26a890a944c66ff","e4fbb6584eb52232eb670d365d8ff9d9c73aa1f5","Altafonte","es","MXB131500007","Altafonte under exclusive license from Ohanian S. de R.L. de C.V.","2015-08-14",null],["4DtFbe2JQrH3dDQVcOkVp6","Nada Fue Un Error - Live In Spain / 2005",159872500,"ab67616d00001e020110f379e66640b2c0e41bce","28b4aea3b19d772e79d53f2887bbc35a25c90fb7","Universal Music Group","es","ES5700500260","Universal Music Spain S.L.","2005-01-01",null]]},"topCities":{"fields":["cid","l"],"rows":[[1000,2306503],[1007,570486],[1008,560561],[1030,531919],[1034,530798]]},"relatedArtists":[]}