{
  "followers": 18995,
  "monthlyListeners": 33283,
  "topCities": {
    "items": [
      {
        "city": "Seattle",
        "country": "US",
        "numberOfListeners": 360,
        "region": "WA"
      },
      {
        "city": "Chicago",
        "country": "US",
        "numberOfListeners": 308,
        "region": "IL"
      },
      {
        "city": "London",
        "country": "GB",
        "numberOfListeners": 276,
        "region": "ENG"
      },
      {
        "city": "Sydney",
        "country": "AU",
        "numberOfListeners": 275,
        "region": "NSW"
      },
      {
        "city": "Melbourne",
        "country": "AU",
        "numberOfListeners": 259,
        "region": "VIC"
      }
    ]
  },
  "worldRank": 0
}
