{
  "followers": 287571,
  "monthlyListeners": 5412999,
  "topCities": {
    "items": [
      {
        "city": "Chicago",
        "country": "US",
        "numberOfListeners": 120469,
        "region": "IL"
      },
      {
        "city": "Los Angeles",
        "country": "US",
        "numberOfListeners": 111570,
        "region": "CA"
      },
      {
        "city": "New York City",
        "country": "US",
        "numberOfListeners": 102363,
        "region": "NY"
      },
      {
        "city": "Atlanta",
        "country": "US",
        "numberOfListeners": 91509,
        "region": "GA"
      },
      {
        "city": "Dallas",
        "country": "US",
        "numberOfListeners": 88725,
        "region": "TX"
      }
    ]
  },
  "worldRank": 0
}
