{
  "followers": 8937727,
  "monthlyListeners": 14305644,
  "topCities": {
    "items": [
      {
        "city": "London",
        "country": "GB",
        "numberOfListeners": 279299,
        "region": "ENG"
      },
      {
        "city": "Milan",
        "country": "IT",
        "numberOfListeners": 220462,
        "region": "25"
      },
      {
        "city": "Sydney",
        "country": "AU",
        "numberOfListeners": 207053,
        "region": "NSW"
      },
      {
        "city": "Toronto",
        "country": "CA",
        "numberOfListeners": 194444,
        "region": "ON"
      },
      {
        "city": "Lagos",
        "country": "NG",
        "numberOfListeners": 175514,
        "region": "LA"
      }
    ]
  },
  "worldRank": 0
}
