{"v":1,"i":"5N9cTRRtmhBTqCvMHVwoX8","tracks":["6jov4DuxPbpX8hQqs2lBW5","6koKhrBBcExADvWuOgceNZ","57DarSfRMIVRCeDBGW0l5S","77Fi5t6oOR6mdAHD2WA08Z","6vuVCtwukUA57ioTnKKeuL","0fK7ie6XwGxQTIkpFoWkd1","040I32EKLxQrkuxQu1pqvT","1ONPCbtvEuoJeVqI40oxAv","2OCX83WxdRlEQEOJhfrzxj","2BMNzg0LldTQRkgzAubHHI","0YieNuEXngayosZN9sMmj7","2p8IUWQDrpjuFltbdgLOag","3w2PO4US2zMxFDxEjWT9yB","7CmQjA7j6CxyPBkH3tP95W","4SNPg0KDZ859vauVTaNg7i","35ISBknsCeZQtq66xABI9g","6GOOcBV0wLoHrH5D9AWA32","6huNf4dutXRjJyGn7f5BPS","4Nh7Umpl8YPFPcggcby6JW","22YkP95GjCfXkWKyU5k1zZ","3azfQHCXEPlyhJtREJ66R5","4Vbo6zQeh7q0FeOJP5sACT","4xvEn1vhrF9JbPFWqTXsH4","75n9WHWZAzhB59xSjIHly4","7xFy1kfgGWJWTpx1vSHBLi","2Xr1dTzJee307rmrkt8c0g","0eaVIYo2zeOaGJeqZ5TwYz","35sZOqVnTQNIGWGURrFdLh","0xoYZ45fgTfyQYREZPN7Sa","6GfWhSJjiD3wd1tvirKC5k","4N1MFKjziFHH4IS3RYYUrU","3H6xZgwRZx8McVUJzmMxWe","5dr58NENsQQaT4oHwTMPgy","4scxvvNN8Dhm5y4p54QamD","1312ZAYpw7aeRQ8GMkbJux","1lbNgoJ5iMrMluCyhI4OQP","7cyrNRyUdZxOOoUk0mddi3","40ds3xedbMkWhszkGnZwxi","2vXKRlJBXyOcvZYTdNeckS","2UtuOyOQ0VxF2sNZU12H3y","0awZwmlC6pxH65KTZpadmX","0WS1qLcXKsCGt5e3dqq30S","3bB97PIqXf7WtkKeuYuXFS","2VyvDGdcVY04cNYou9MFVX","2xpeEb2moFy7dRinc7tUnz","3B4etxytImrRKQgV3XHjnR","6dOtVTDdiauQNBQEDOtlAB","51ZQ1vr10ffzbwIjDCwqm4","35DzYSdOBggQOkMWAc99i1","0oiv4E896TUTTeQU0cmIui","7qfvLOlyhDIYYCO1C3cacU","3e9GHujFJkDT6hSZTAw1yR","0FIDCNYYjNvPVimz5icugS","1Ahp4PZ1vzdbzBCedUrsqI","5NL4Z4UexKu7BDdilyhzQZ","5ITV0zqzjOYfFWpW0xBmRa","3N3Ahnpz2Ul57wCJWOagAa","1P9ZF3ZxRWNTDgJkZOgkI9","58paGzudpZjF11LrsgkxCP","2uIX8YMNjGMD7441kqyyNU","3ipy5ap1gVSdERpF5ays6F","51ODNNDZm21HU7wI7cccRr","6IAPVBbwl09PPHLWMJ9vuk","4b93D55xv3YCH5mT4p6HPn","1fAE0TQ3xblvOgnmM7yL1s","39glDGcpBhLVMSsQhvtqHR","1LzvTGwdQEnAy9OexQ3TYs","6LH1KKXEw1K8UEKMK75qyz","0scd3nh27AYTNXo0KHRmsG","3c8iiZGfEammKJuWTErE5x","7gntSuY5q2Icn5dOytaXki","2d3QlXE6FXFDeodiS66yjM","4eyHf2QbZZKoPWpZBYc0KX","4ZH03VC3uJk7uKk7CwsBqH","5gOyjqIifZ9NqVcaIIlqv7","3AWDeHLc88XogCaCnZQLVI","19kHhX6f6EfLU7rcO3RqjO","7HXUFIILHAhS6esiRy5Ibz","1osIOdkR2nn1NUTBne4e6D","1zi7xx7UVEFkmKfv06H8x0","4lWnh8J3XsWTtG20xWFjfF","4CJHf9ymP2CkIacTIuIkAZ","7BM4RPgiL2V6argIf8QEU4","6v2lvDawIkVB18FD0ZrOWN","0M8nfWI3cAkYcXNTB0mrCN","6LhKOUggIjsl0P0xiFUAxd","5xdVqHtFS0eLuNp4Z8Wbpa","1Vx2rSaR2GNuCViAvTOdr6","7aqQC9GAOSSODVk0oKJjLZ","3nnStd7PMGgrN0tfmdhv3j","1GpslorH7Gi64x8uodyvfO","4yaPPFIafaVaMRHZ5IHkbA","4JxY3pNkxMKHjrPiOGQqcQ","26b3oVLrRUaaybJulow9kz","2hloaUoRonYssMuqLCBLTX","7qjZnBKE73H4Oxkopwulqe","4VWahNC3hzIZpJsb1aNBB8","6JVUbFM7sTwgRqyA5jcN9G","03A9CAoRTrqSeaEEERXuNT","5RR5xHuWc1WZfA2YkcGt4P","25MPSH5b95vAZgyQq9lt4M","221qmpQeBNV87sUjQeUTVH","6uT2TsDrCrXue7ROEfNeGN","2GwQ33xxkI5sVy8JOcMRVg","0nZUQdt97RJ429I0FuAO2r","5mCPDVBb16L4XQwDdbRUpz","4VxTzYm00mg82MuoT35Ja7","31mzt4ZV8C0f52pIz1NSwd","2pN5GwdTWbFZNRgFIRlW7J","4sYbZjRCyaFqCtJ2Uvfh8B","6wlopbfuodLVb5hMSa2TR2","3JhpsFR2yZhprzqXuzwGqj","2v0AG62ZHtD3I4YmTb3WYM","2RJo6RNV5dpjLh6Co4nPsI","5G2f63n7IPVPPjfNIGih7Q","7wAuksvJErTLz0OHTDJPIa","5M03DZT7oEC0Ma3Eri5ZlY","2aPTvyE09vUCRwVvj0I8WK","697Ub7j26uCkn3VtWSucG3","2mdEsXPu8ZmkHRRtAdC09e","4B0JvthVoAAuygILe3n4Bs","1NKjc6bRHutPoaVtYclFC3","4udjo5nLK61pKajakfrndc","0smB5zD5CJYMtdXvS2qS5A","0DyUraoJXK9dByAr0CaZjV","3xSeXxD1kT2DXyWBbDAIxB","5YGSoLBgQC6Mt58qFJvGwU","2p3SjPcPdxZ9rYYzS6l6F0","2uvE4L5ZsYKpv8hbK4TIOt","5Mk1tgVrSuoWWwPVFNS0jB","5dphB03NIaqz4L3q76McSI","7jUrpnUzBYpRIUb7GxjbNs","4BsLwvaJOTOHDNg7xMpvrL","1fLTi1wA2FPONA5SAIoKJX","2bJvI42r8EF3wxjOuDav4r","0ntH5kwbbeGk7rShowaq4j","51TCxtQ1u4Qi655ekjDCZD","5mg9TnSnfc89gcYStpOsVL","1JKo6V7VgO6MM2uj7iVkHh","23Z3bbYcl1PdcPJemLa4zc","0Rkdov9ktWGjqOqy9MQ8XP","169pWCmfvVazzcL4EXFPgL","4fUK2q5ERoi97E3g2kwB8c","3zPco1u9i9bCjkG5pngR5t","00eHZjj2Xb7yaNTGIJ9mKU","09DuyOnHYxaTrob9qVxZnH","6lnmfGslDQnFc4973EpAs2","5FMyXeZ0reYloRTiCkPprT","2p6Fh5ruk8YUaO43huubHW","0QCIpQV3twfqo9kh0t8Zza","3RJqGQaU5C6olAtsaO7hjc","178n1tTLTmsIyxBTQdcAJM","1dcK8O2qEq7E34o4ImQEco","2HRqTpkrJO5ggZyyK6NPWz","2ycpJAE8kxNRhwXRsbFKlu","4SymlUG2OhBgiQWcDZ0OQy","2jWZ9NZotZb2hN5obKx2FA","5nPbKG04fhLkIAjcPFaZq7","4AXUWmQcDpRpULGY5ge6aV","541sN2qNfIlllGn9nGOQoC","3bWEONUAlVrGAB4NqQiT2R","6PTgSuFz9JqQ1o0jTYOuvX","2pHVRpdFGyVvM4fkCv6r0q","6w8OHGviIdhA7YGZ0GpDqI","4dnjLEblR5XKUMJ5ELQceh","4E63weMCaNZuGPEFMnuEi8","4tVASOccgcigdCfwUamZCh","1akvU6dDo0nCaIZPQo7bRY","1y62v08lkqdPTBj7si8tnA","4JdrBjzboUgxVztpIRFp8t","2s4AcE9n80mSHl87lp4gIm","3cZajhyr8LmtPfHZ9296tj","1Ph96WpdjNlwD6iKRE2Xa3","2OpBganfGk2GVdSlRdxzaX","51aYPHVdOL9sIPOZj9dlXK","6hmhG1b4LEyNuashVvuIAo","1mZF9TEc7gpw7by7NCZSKr","7ASFZh1D0DPZro7UXUKGmd","1BJJbSX6muJVF2AK7uH1x4","6czM6UMQD9qE5GAUp68oud","6a23CwL8bVeizmNRR9AACs","4pAl7FkDMNBsjykPXo91B3","11zf7m4vw9Ze7cer9Nyhk1","3wlEt7tgbcyowpdlcnCwfz","13EHxr8bqdfqwXtyp411bf","2RdEC8Ff83WkX7kDVCHseE","0vsW1vAlNYiy9Y5briGT8Y","4sOLtnLeIFwO4YUUSV5DM5","0nFa4Lfve6l7LmqFe553OC","3M0lSi5WW79CXQamgSBIjx","6q8onrzcka32nGVrnWYGBQ","5cF53kSZ8g4YzZqHEJzR9o","3WID8m6M9eEQ1w1k486vMc","0B7tnohfi83RQquo2JRHrL"],"synced_at":"2025-11-11T13:49:26+00:00Z","synced_month":"2025-11","sync_count":1}