{"v":1,"i":"5ZBGONg1ey0BOoombzNfJV","tracks":["3AhXZa8sUQht0UEdBJgpGc","3L60Vu9qmY6fg2QroRIxgi","53jhILFzXhKPHAfsLoLUwA","0jvN7eQJJt4nxQzgQfZ1SP","4Q3ERWBrb4lhDvAPyANjY5","5t9KYe0Fhd5cW6UYT4qP8f","6z2AyfE9GZxoHqJVSA4NgN","0PNt5WTw092eED0ru9SuIp","6Qb7gtV6Q4MnUjSbkFcopl","5ynO8cYFjDwELIZfFHHeYe","4egy2d8QiyXn5tzVQiptTb","7LRMbd3LEoV5wZJvXT1Lwb","7vidktgNZFQylTgH1GEnMs","4uip0lLkMKl1nwchsdXs1r","2Vim06YsRb4uJRpbeq6NR6","52dm9op3rbfAkc1LGXgipW","2TofEeQobQ9YoK7EFds698","7FwBtcecmlpc1sLySPXeGE","7F02x6EKYIQV3VcTaTm7oN","2AxCeJ6PSsBYiTckM0HLY7","5Wj1rJnCLpMHdLaxsFtJLs","3IsWNivZZHYURT2kTIvBDU","2oSpQ7QtIKTNFfA08Cy0ku","6aqm56xP40foYBBtAWWrnY","0l49BLiXUhHD2A92ONuQ7k","42o3gy9e8dzBHvQE991ad8","0Z3xhSOhrawLV81YdiDiiJ","6G3NoUqDpqD3Rgfel2pD6s","2PzU4IB8Dr6mxV3lHuaG34","0gCJkpD0RhF2rjiALLHBQL","02Y7UtZLh7SbhYsYG5N7Rr","1OEoNpiyqBghuEUaT6Je6U","4vpeKl0vMGdAXpZiQB2Dtd","0qRR9d89hIS0MHRkQ0ejxX","5RgFlk1fcClZd0Y4SGYhqH","1QaJWSCk3UMKLotnPCIHh1","4yugZvBYaoREkJKtbG08Qr","3T8dfE0azJUmXJA3QlmiZ5","1lqMLr9Wj7SM2F9AikGcxN","55WrYzR1SHfXeeU6DJbk3Y","777NOXupZkFdg8zlPMoVqc","2ZS3jFe6p8UoVyrY5jWBlF","29HbMTL672MugzhklYvStz","4vhVDkSx9RSb2k6mWFMYNI","67HxeUADW4H3ERfaPW59ma","0lzNXoZINVBLHWNIxKxWOo","0tK1Ya57nOsgD0nGndjpdI","0iOZM63lendWRTTeKhZBSC","744hdHz3CORMz3FcU230C4","2wvMC5EyaaYQwBfiwwY2xE","6pxWv6GV35VGmcPf5dh6CH","06FcMPcosZg13x2QODDDK6","07q0QVgO56EorrSGHC48y3","7n3WO6ESKS1uCI9fgkGs66","48i055G1OT5KxGGftwFxWy","1AGridgU0QAWZykQReGWk5","7uPmQttafLiJyju14JREY4","52DKGPMQ21DauCR19pQ0BK","587bVBCHYW5Q2VNRLig4AS","4Zc7TCHzuNwL0AFBlyLdyr","0v0XYK0pLgsPiq5u4FKHaw","4BP3uh0hFLFRb5cjsgLqDh","4BVE5tIIpYabZcYCbephNW","7j74lucZ59vqN67Ipe2ZcY","5dAxeuDkIkpa6wZpMOuG9i","39C5FuZ8C8M0QI8CrMsPkR","7L3b6iaVhDVjfo52Hbvh9Z","4rVvheUQ2wQpn5uXX5l0gS","2miIOgni3EEut8pvYcxeYn","5gOd6zDC8vhlYjqbQdJVWP","3oJtUnnt5uYPtzulIbLw3D","6gXrEUzibufX9xYPk3HD5p","0JNZGIavoUrdup1NsgJOQs","2Y90nL1ohB4sgYELDs7uNx","6QAsrXPnMSXIbV0yEJHlEX","6kooDsorCpWVMGc994XjWN","4Mqs0h95KAeNiGp7u4udlt","11DjZQEZ69EXLo77HVj6yW","1Y373MqadDRtclJNdnUXVc","788cNfvhhitTb5T8GORmqj","5m6livL7ccIS92wq16n52r","3h04eZTnmFLRMjZajbrp2R","3OUExRnXWXzMc5sJ39u7ru","0ofHAoxe9vBkTCp2UQIavz","7cy1bEJV6FCtDaYpsk8aG6","7snQQk1zcKl8gZ92AnueZW","3IOQZRcEkplCXg6LofKqE9","2mEVBiiVvOAYjvzM3OED0T","5tmrnhMxx39jnu3kjopMdP","2vj0Vs7bcIJMbkEc9VlQkA","4TIJ7zSBNejpoIPaWpWRKc","1y4fbtHSJLqpaQXduQw88e","3gxEZXUjrNbl3TlSrTGbR5","67hbP9PFQZrb4XZc3TzB0s","7aOor99o8NNLZYElOXlBG1","0f7VY69zhtS20Xm5PVYCm5","0LYI2vHQ07bYRWqw0lXLhJ","17QTsL4K9B9v4rI8CAIdfC","5cB8rxBcAtzyB3u7Y8xOLK","6H3kDe7CGoWYBabAeVWGiD","40h65HAR8COEoqkMwUUQHu","4hupcimlg3UBbW1kAQ6vrT","5WyuRWUcOOhAic0tj9Pl28","7nemcVsXVFZF01iqpIIo2Y","26QKxvjlCo2fSd3T4c8Zpb","2wnsBaxrmkthIFAm6vqCuX","3BdHMOIA9B0bN53jbE5nWe","5Hk4Mpex0s2ndUpDQ5v2rU","2fuCquhmrzHpu5xcA1ci9x","6wpGqhRvJGNNXwWlPmkMyO","34OzAaQeAWlFnZBSyUAtRh","4nXkbcTj3nyww1cHkw5RAP","6ek9SiEj5a65WIs2EV7qiM","4gMgiXfqyzZLMhsksGmbQV","5VErNsWF69eD0HiBt2vWcH","3ix6K4wZY29bCujrSznwFZ","0vTvkf24wkCG3DTKgoNnih","4KROoGIaPaR1pBHPnR3bwC","41RMsOmfx1B2n3Z44ELOb5","1QLr0zOu6fv5hLEHOwdr21","1gVVSmhWjci8l9Vrsl6HaS","7Bz8yww6UMbTgTVLG6zbI4","0KZodeWxqxd88F9wY1cqgs","1JjkKaPVEjisTExWL3C9CD","5p3JunprHCxClJjOmcLV8G","05RgAMGypEvqhNs5hPCbMS","72Z17vmmeQKAg8bptWvpVG","31AOj9sFz2gM0O3hMARRBx","7w2s5Wj0LPNhUkVCt8av09","4dBI72rgkmG0gTzswyBTzz","2aibwv5hGXSgw7Yru8IYTO","4rDbp1vnvEhieiccprPMdI","0upLyFR8Rr52ZpMp5esQoq","62AuGbAkt8Ox2IrFFb8GKV","3vMfr8H7hGbOLoddLdCQU4","6fybp4N6eW3bsFAvARxyVe","63T7DJ1AFDD6Bn8VzG6JE8","6PgVDY8GTkxF3GmhVGPzoB","042v1NacbKJzCyi6nBme7T","08xsXR637CEqbxJmpFcuSA","6zeE5tKyr8Nu882DQhhSQI","3EYOJ48Et32uATr9ZmLnAo","5izGeTxueiFX1UPFGohY9w","3v9xlH6BpmRbqL7hgNJhfT","5UgT7w6zVZjP3oyawMzbiK","3TO7bbrUKrOSPGRTB5MeCz","3KPwt1LBpt1jVSHz8GXERo","7B9F9nLxe7MZgZ68Jj86Fn","0cJPLFrlV7TTCyPLupHzcH","3lh3iiiJeiBXHSZw6u0kh6","0yJvWbn8xQKiDZ84VN5lQG","6XUHsYE38CEbYunT983O9G","1PC5GV3OaoXx5em8ttQOMI","4e9hUiLsN4mx61ARosFi7p","0P7DoyGrr4Wp9w5TotEtUC","1TKTiKp3zbNgrBH2IwSwIx","2Wf4IsWzhBgVR9uUDuktFB","2g3JAKjKruTL40VffoGLmg","2RlgNHKcydI9sayD2Df2xp","0x2wtJbtJrox3SDmnMj97x","3fkPMWQ6cBNBLuFcPyMS8s","2EqlS6tkEnglzr7tkKAAYD","6mFkJmJqdDVQ1REhVfGgd1","1ynmMEK1fkyiZ6Z6F3ThEt","4IHc6SzGPnzSPuHVEPzpJc","73TxYZd0lBCVRrHawrAglA","0gzqZ9d1jIKo9psEIthwXe","6vZZtivPrtpggT5SSXsYTy","7HKez549fwJQDzx3zLjHKC","77oU2rjC5XbjQfNe3bD6so","4DMKwE2E2iYDKY01C335Uw","5jzma6gCzYtKB1DbEwFZKH","1orVKbp6vqtfAPOmvRofVq","11oBg7EA3BgPLWrIx4Rv7D","7Ar4G7Ci11gpt6sfH9Cgz5","1WYokrkFOb9TFVuTrmxTTt","5l9c6bJmzvftumhz4TMPgk","7hVhRCDV100Jq26NGR7adw","1ml1uvYYq9uChP1fZd6MtG","3dmqIB2Qxe2XZobw9gXxJ6","44aTAUBF0g6sMkMNE8I5kd","3dPQuX8Gs42Y7b454ybpMR","4jLv3tDBu8ww2R07DvL12s","5CGpPUcUahMuLzkNK9ZgPP","47bXIv24jthL4vzZy3j7CY","3tIvHt7VaIenprWXrYzgwb","2d4e45fmUnguxh6yqC7gNT","0PQ51hZtABYRaXNHkVpAfD","67eX1ovaHyVPUinMHeUtIM","1J5XEPamp7iQaCU0aFuMnd","2olVm1lHicpveMAo4AUDRB","1IqFh00G2kvvMm8pRMpehA"],"synced_at":"2025-11-11T13:26:41+00:00Z","synced_month":"2025-11","sync_count":1}